{
 "name": "Xiaomi Mi 9X",
 "codename": "",
 "picture": "https://fdn2.gsmarena.com/vv/bigpic/xiaomi-mi-9-.jpg",
 "url": "https://www.gsmarena.com/xiaomi_mi_9x-9650.php",
 "specs": {
  "Network": [
   {
    "Technology": "GSM / CDMA / HSPA / LTE",
    "2G bands": "GSM 850 / 900 / 1800 / 1900 - SIM 1 & SIM 2",
    "info": "CDMA 800 & TD-SCDMA",
    "3G bands": "HSDPA 850 / 900 / 1700(AWS) / 1900 / 2100 ",
    "4G bands": " LTE (unspecified)",
    "Speed": "HSPA, LTE-A"
   }
  ],
  "Launch": [
   {
    "Announced": "Not announced yet",
    "Status": "Cancelled"
   }
  ],
  "Body": [
   {
    "Dimensions": "-",
    "Weight": "-",
    "SIM": "Dual SIM (Nano-SIM, dual stand-by)"
   }
  ],
  "Display": [
   {
    "Type": "Super AMOLED capacitive touchscreen, 16M colors",
    "Size": "6.39 inches, 100.2 cm2",
    "Resolution": "1080 x 2340 pixels, 19.5:9 ratio (~403 ppi density)",
    "info": "DCI-P3"
   }
  ],
  "Platform": [
   {
    "OS": "Android 9.0 (Pie); MIUI 10",
    "Chipset": "Qualcomm SDM675 Snapdragon 675 (11 nm)",
    "CPU": "Octa-core (2x2.0 GHz Kryo 460 Gold & 6x1.7 GHz Kryo 460 Silver)",
    "GPU": "Adreno 612"
   }
  ],
  "Memory": [
   {
    "Card slot": "No",
    "Internal": "64GB 6GB RAM"
   }
  ],
  "Main Camera": [
   {
    "Triple": "48 MP, f/1.8, 27mm (wide), 1/2.0\", 0.8\u00b5m, PDAF\r\n8 MP, (telephoto), PDAF, 2x optical zoom\r\n13 MP, (wide)",
    "Features": "Dual-LED flash, HDR, panorama",
    "Video": "2160p@30/60fps, 1080p@30/120/240fps, 1080p@960fps"
   }
  ],
  "Selfie camera": [
   {
    "Single": "32 MP, f/2.0, 26mm (wide), 1/2.8\", 0.8\u00b5m",
    "Features": "HDR",
    "Video": "1080p@30fps"
   }
  ],
  "Sound": [
   {
    "Loudspeaker ": "Yes",
    "3.5mm jack ": "No"
   }
  ],
  "Comms": [
   {
    "WLAN": "Wi-Fi 802.11 a/b/g/n/ac, dual-band, Wi-Fi Direct, DLNA, hotspot",
    "Bluetooth": "5.0, A2DP, LE, aptX HD",
    "GPS": "Yes, with A-GPS, GLONASS, GALILEO",
    "NFC": "Yes",
    "Infrared port": "Yes",
    "Radio": "No",
    "USB": "2.0, Type-C 1.0 reversible connector, USB On-The-Go"
   }
  ],
  "Features": [
   {
    "Sensors": "Fingerprint, accelerometer, gyro, proximity, compass"
   }
  ],
  "Battery": [
   {
    "info": "Non-removable Li-Po 3300 mAh battery",
    "Charging": "Fast battery charging 18W"
   }
  ],
  "Misc": [
   {
    "Colors": "Various"
   }
  ]
 }
}